setup.py
lp_rest_kernel/__init__.py
lp_rest_kernel.egg-info/PKG-INFO
lp_rest_kernel.egg-info/SOURCES.txt
lp_rest_kernel.egg-info/dependency_links.txt
lp_rest_kernel.egg-info/requires.txt
lp_rest_kernel.egg-info/top_level.txt
lp_rest_kernel/rest/__init__.py
lp_rest_kernel/rest/file.py