Metadata-Version: 1.0
Name: lp-rest-kernel
Version: 1.0.0
Summary: Basic REST kernel.
Home-page: https://github.com/InfrabelLinux/linuxportal-rest-kernel
Author: Infrabel Linux Team
Author-email: linux@infrabel.be
License: Apache
Platform: UNKNOWN
